pytest_scrutinize/__init__.py
pytest_scrutinize/data.py
pytest_scrutinize/io.py
pytest_scrutinize/mocks.py
pytest_scrutinize/plugin.py
pytest_scrutinize/plugin_xdist.py
pytest_scrutinize/timer.py
pytest_scrutinize/utils.py
pytest_scrutinize-0.1.6.dist-info/METADATA
pytest_scrutinize-0.1.6.dist-info/WHEEL
pytest_scrutinize-0.1.6.dist-info/entry_points.txt
pytest_scrutinize-0.1.6.dist-info/RECORD
