Metadata-Version: 2.3
Name: pytest-scrutinize
Version: 0.1.6
Summary: Scrutinize your pytest test suites for slow fixtures, tests and more.
Project-URL: Homepage, https://github.com/orf/pytest-scrutinize/
Project-URL: Repository, https://github.com/orf/pytest-scrutinize.git
Project-URL: Issues, https://github.com/orf/pytest-scrutinize/issues
Author-email: Thomas Forbes <tom@tomforb.es>
License: MIT License
Keywords: pytest,timing
Classifier: Development Status :: 4 - Beta
Classifier: Intended Audience :: Developers
Classifier: License :: OSI Approved :: MIT License
Classifier: Programming Language :: Python :: 3
Classifier: Programming Language :: Python :: 3.9
Classifier: Programming Language :: Python :: 3.10
Classifier: Programming Language :: Python :: 3.11
Classifier: Programming Language :: Python :: 3.12
Requires-Python: >=3.9
Requires-Dist: pydantic<=3,>=2
Requires-Dist: pytest>=6
